batmon.py
batmon-0.0.5.dist-info/DESCRIPTION.rst
batmon-0.0.5.dist-info/METADATA
batmon-0.0.5.dist-info/RECORD
batmon-0.0.5.dist-info/WHEEL
batmon-0.0.5.dist-info/entry_points.txt
batmon-0.0.5.dist-info/metadata.json
batmon-0.0.5.dist-info/top_level.txt
