Metadata-Version: 2.0
Name: batmon
Version: 0.0.5
Summary: A Python script to provide notifications of battery life
Home-page: https://github.com/rcoh/batmon
Author: Russell Cohen
Author-email: rcoh@rcoh.me
License: UNKNOWN
Project-URL: Bug Reports, https://github.com/rcoh/batmon/issues
Project-URL: Source, https://github.com/rcoh/batmon/
Keywords: battery monitor xmonad xmobar
Platform: UNKNOWN
Classifier: Development Status :: 3 - Alpha
Classifier: License :: OSI Approved :: MIT License
Classifier: Programming Language :: Python :: 3.6
Requires-Dist: click
